aiosox/__init__.py
aiosox/asyncapi/__init__.py
aiosox/asyncapi/bindings.py
aiosox/asyncapi/channel.py
aiosox/asyncapi/components.py
aiosox/asyncapi/enums.py
aiosox/asyncapi/exceptions.py
aiosox/asyncapi/main.py
aiosox/asyncapi/message.py
aiosox/asyncapi/operation.py
aiosox/asyncapi/parameter.py
aiosox/asyncapi/reference.py
aiosox/asyncapi/schema.py
aiosox/asyncapi/security.py
aiosox/asyncapi/server.py
aiosox/asyncapi/tag.py
aiosox/kafka/__init__.py
aiosox/kafka/utils.py
aiosox/ponicode/__init__.py
aiosox/ponicode/utils_test.py
aiosox/sio/__init__.py
aiosox/sio/actors.py
aiosox/sio/client_manager.py
aiosox/sio/enums.py
aiosox/sio/namespace.py
aiosox/sio/ponicode/__init__.py
aiosox/sio/ponicode/namespace_test.py
aiosox/sio/ponicode/server_test.py
aiosox/sio/schemas.py
aiosox/sio/server.py
aiosox/utils.py
aiosox-0.3.0.dist-info/WHEEL
aiosox-0.3.0.dist-info/METADATA
aiosox-0.3.0.dist-info/RECORD
