Metadata-Version: 2.1
Name: aiosox
Version: 0.3.0
Summary: ⛓️ Combination of asyncapi(documentation) & socketio pub/sub using aiokafka as the client manager  multinode backend services
Home-page: https://gitlab.com/arieutils/aiosox
Keywords: fastapi,asyncapi,kafka,aiokafka,socketio,pubsub,websockets
Author: Arie
Author-email: ariesorkin3@gmail.com
Requires-Python: ==3.11.1
Classifier: Programming Language :: Python :: 3
Requires-Dist: aiokafka (>=0.8.0,<0.9.0)
Requires-Dist: anyio[trio] (>=3.6.2,<4.0.0)
Requires-Dist: fastapi (>=0.88.0,<0.89.0)
Requires-Dist: mkdocs (>=1.4.2,<2.0.0)
Requires-Dist: mkdocs-material (>=9.0.2,<10.0.0)
Requires-Dist: orjson (>=3.8.3,<4.0.0)
Requires-Dist: pydantic (>=1.10.4,<2.0.0)
Requires-Dist: python-socketio (>=5.7.2,<6.0.0)
Requires-Dist: uvicorn[standard] (>=0.20.0,<0.21.0)
Project-URL: Documentation, https://arieutils.gitlab.io/aiosox/
Project-URL: Repository, https://gitlab.com/arieutils/aiosox
